eclinicio/__init__.py
eclinicio/dates.py
eclinicio/decorators.py
eclinicio/imports.py
eclinicio/meta.py
eclinicio/urlimport.py
eclinicio/utils.py
eclinicio/cli/__init__.py
eclinicio/cli/sql.py
eclinicio/net/__init__.py
eclinicio/net/evloop.py
eclinicio/net/mail.py
eclinicio/net/server_factory.py
eclinicio/net/sslsocket.py
eclinicio/win32/__init__.py
eclinicio/win32/utils.py
eclinicio-0.2.0.dist-info/METADATA
eclinicio-0.2.0.dist-info/WHEEL
eclinicio-0.2.0.dist-info/top_level.txt
eclinicio-0.2.0.dist-info/RECORD
